data_inspector/__init__.py
data_inspector/data_inspector.py
data_inspector-1.5.5.dist-info/LICENCE.txt
data_inspector-1.5.5.dist-info/METADATA
data_inspector-1.5.5.dist-info/WHEEL
data_inspector-1.5.5.dist-info/top_level.txt
data_inspector-1.5.5.dist-info/RECORD
