Metadata-Version: 2.1
Name: data-inspector
Version: 1.5.5
Summary: This module brings different functions to make EDA, data cleaning easier.
Home-page: https://github.com/AmitHasanShuvo/data-inspector
Author: Kazi Amit Hasan
Author-email: kaziamithasan89@gmail.com
License: UNKNOWN
Keywords: eda
Platform: UNKNOWN
Classifier: Programming Language :: Python :: 3
Classifier: License :: OSI Approved :: MIT License
Classifier: Operating System :: OS Independent
Requires-Dist: pandas (==1.1.2)
Requires-Dist: matplotlib (==3.1.2)
Requires-Dist: numpy (==1.18.5)
Requires-Dist: seaborn (==0.11.1)
Requires-Dist: scipy (==1.6.2)
